sphinx_zon_theme/__init__.py
sphinx_zon_theme/layout.html
sphinx_zon_theme/theme.conf
sphinx_zon_theme/static/zon.css
sphinx_zon_theme/static/zon.ico
sphinx_zon_theme/static/zon.png
sphinx_zon_theme-1.4.4.dist-info/LICENSE
sphinx_zon_theme-1.4.4.dist-info/METADATA
sphinx_zon_theme-1.4.4.dist-info/WHEEL
sphinx_zon_theme-1.4.4.dist-info/entry_points.txt
sphinx_zon_theme-1.4.4.dist-info/top_level.txt
sphinx_zon_theme-1.4.4.dist-info/RECORD
