Metadata-Version: 2.1
Name: sphinx-zon-theme
Version: 1.4.4
Summary: Sphinx Theme for ZEIT ONLINE
Home-page: https://github.com/zeitonline/sphinx_zon_theme/
Author: Wolfgang Schnerring <wolfgang.schnerring@zeit.de>
Author-email: wolfgang.schnerring@zeit.de
License: MIT
Classifier: License :: OSI Approved :: MIT License
Classifier: Programming Language :: Python
Classifier: Programming Language :: Python :: 2
Classifier: Programming Language :: Python :: 3
Classifier: Framework :: Sphinx
Classifier: Framework :: Sphinx :: Theme
License-File: LICENSE
Requires-Dist: sphinx-rtd-theme (>=1.0.0)
Requires-Dist: setuptools
